bob/__init__.py
bob/bio/__init__.py
bob/bio/vein/__init__.py
bob/bio/vein/algorithm/Correlate.py
bob/bio/vein/algorithm/HammingDistance.py
bob/bio/vein/algorithm/MiuraMatch.py
bob/bio/vein/algorithm/__init__.py
bob/bio/vein/config/__init__.py
bob/bio/vein/config/maximum_curvature.py
bob/bio/vein/config/principal_curvature.py
bob/bio/vein/config/repeated_line_tracking.py
bob/bio/vein/config/wide_line_detector.py
bob/bio/vein/config/database/__init__.py
bob/bio/vein/config/database/utfvp_1vsall.py
bob/bio/vein/config/database/utfvp_full.py
bob/bio/vein/config/database/utfvp_nom.py
bob/bio/vein/config/database/verafinger_contactless_nom.py
bob/bio/vein/database/__init__.py
bob/bio/vein/database/database.py
bob/bio/vein/database/roi_annotation.py
bob/bio/vein/database/utfvp.py
bob/bio/vein/database/verafinger_contactless.py
bob/bio/vein/extractor/MaximumCurvature.py
bob/bio/vein/extractor/NormalisedCrossCorrelation.py
bob/bio/vein/extractor/PrincipalCurvature.py
bob/bio/vein/extractor/RepeatedLineTracking.py
bob/bio/vein/extractor/WideLineDetector.py
bob/bio/vein/extractor/__init__.py
bob/bio/vein/preprocessor/__init__.py
bob/bio/vein/preprocessor/crop.py
bob/bio/vein/preprocessor/filters.py
bob/bio/vein/preprocessor/mask.py
bob/bio/vein/preprocessor/normalize.py
bob/bio/vein/preprocessor/preprocessor.py
bob/bio/vein/preprocessor/utils.py
bob/bio/vein/script/__init__.py
bob/bio/vein/script/blame.py
bob/bio/vein/script/compare_rois.py
bob/bio/vein/script/validate.py
bob/bio/vein/script/view_sample.py
bob.bio.vein-5.0.1.dist-info/COPYING
bob.bio.vein-5.0.1.dist-info/METADATA
bob.bio.vein-5.0.1.dist-info/WHEEL
bob.bio.vein-5.0.1.dist-info/entry_points.txt
bob.bio.vein-5.0.1.dist-info/top_level.txt
bob.bio.vein-5.0.1.dist-info/RECORD
