Metadata-Version: 2.1
Name: bob.bio.vein
Version: 5.0.1
Summary: Vein Recognition Library
Author-email: Andre Anjos <andre.anjos@idiap.ch>, Pedro Tome <pedro.tome@idiap.ch>
License: GPLv3 License
Project-URL: documentation, https://www.idiap.ch/software/bob/docs/bob/bob.bio.vein/v5.0.1/sphinx/
Project-URL: homepage, https://pypi.org/project/bob.bio.vein/
Project-URL: repository, https://gitlab.idiap.ch/bob/bob.bio.vein
Project-URL: changelog, https://gitlab.idiap.ch/bob/bob.bio.vein/-/releases
Keywords: bob,biometric recognition,evaluation,vein
Classifier: Framework :: Bob
Classifier: Development Status :: 4 - Beta
Classifier: Intended Audience :: Science/Research
Classifier: License :: OSI Approved :: GNU General Public License v3 (GPLv3)
Classifier: Natural Language :: English
Classifier: Programming Language :: Python
Classifier: Programming Language :: Python :: 3
Classifier: Topic :: Scientific/Engineering :: Artificial Intelligence
Classifier: Topic :: Software Development :: Libraries :: Python Modules
Requires-Python: >=3.9
License-File: COPYING
Requires-Dist: bob ==12.1.1
Requires-Dist: bob.io.base ==5.1.1
Requires-Dist: bob.bio.base ==8.1.1
Requires-Dist: clapper ~=1.0
Requires-Dist: docopt ~=0.6
Requires-Dist: matplotlib ~=3.8
Requires-Dist: numpy ~=1.26
Requires-Dist: pillow ~=10.2
Requires-Dist: schema ~=0.7
Requires-Dist: scikit-image ~=0.19
Requires-Dist: scipy ~=1.10
Provides-Extra: doc
Requires-Dist: sphinx ; extra == 'doc'
Requires-Dist: sphinx-rtd-theme ; extra == 'doc'
Requires-Dist: sphinx-autodoc-typehints ; extra == 'doc'
Requires-Dist: auto-intersphinx ; extra == 'doc'
Requires-Dist: sphinxcontrib-programoutput ; extra == 'doc'
Provides-Extra: qa
Requires-Dist: pre-commit ; extra == 'qa'
Provides-Extra: test
Requires-Dist: pytest ; extra == 'test'
Requires-Dist: pytest-cov ; extra == 'test'
Requires-Dist: coverage ; extra == 'test'
